eval/.env.example
eval/.gitignore
eval/README.md
eval/__init__.py
eval/__main__.py
eval/cli.py
eval/config.yaml
eval/run_scenario.py
eval/framework/__init__.py
eval/framework/config.py
eval/framework/conversation.py
eval/framework/conversation_completion.py
eval/framework/evaluator.py
eval/framework/httpx_mock_patch.py
eval/framework/metrics.py
eval/framework/mock_http.py
eval/framework/mock_server.py
eval/framework/runner.py
eval/framework/training_data.py
eval/framework/user_agent.py
eval/framework/workspace.py
eval/framework/yaml_loader.py
eval/mock/generators/create_dump.py
eval/mock/generators/generate_mock_data.py
eval/mock/generators/generate_sqlite_fixture.py
eval/mock/generators/load_dump.py
eval/mock/projects/README.md
eval/mock/projects/acme-docs/database/document_entities.jsonl
eval/mock/projects/acme-docs/database/documents.jsonl
eval/mock/projects/acme-docs/database/entities.jsonl
eval/mock/projects/acme-docs/database/entity_relationships.jsonl
eval/mock/projects/acme-docs/integrations/analytics/bottom-pages.json
eval/mock/projects/acme-docs/integrations/analytics/declining-pages.json
eval/mock/projects/acme-docs/integrations/analytics/domain-summary.json
eval/mock/projects/acme-docs/integrations/analytics/top-pages.json
eval/mock/projects/acme-docs/integrations/analytics/trending-pages.json
eval/mock/projects/acme-docs/integrations/cms/sanity/article-1.json
eval/mock/projects/acme-docs/integrations/cms/sanity/article-2.json
eval/mock/projects/acme-docs/integrations/cms/sanity/publish-response.json
eval/mock/projects/acme-docs/integrations/cms/sanity/query-results.json
eval/mock/projects/acme-docs/integrations/cms/sanity/types.json
eval/mock/projects/acme-docs/integrations/research/hackernews-top.json
eval/mock/projects/acme-docs/integrations/research/perplexity-ai-trends.json
eval/mock/projects/acme-docs/integrations/research/perplexity-fastapi.json
eval/mock/projects/acme-docs/integrations/research/reddit-dataeng.json
kurt_core-0.3.0.dist-info/METADATA
kurt_core-0.3.0.dist-info/WHEEL
kurt_core-0.3.0.dist-info/entry_points.txt
kurt_core-0.3.0.dist-info/RECORD
