Metadata-Version: 2.4
Name: kurt-core
Version: 0.3.0
Summary: Document intelligence CLI - Transform documents into structured knowledge graphs
Author-email: huraultj <julien.hurault+boringdata@sumeo.io>
Requires-Python: >=3.10
Requires-Dist: aiosqlite>=0.19.0
Requires-Dist: alembic>=1.13.0
Requires-Dist: click>=8.1.0
Requires-Dist: dbos>=0.9.0
Requires-Dist: dspy>=2.5.0
Requires-Dist: feedparser>=6.0.0
Requires-Dist: firecrawl-py>=1.0.0
Requires-Dist: greenlet>=3.0.0
Requires-Dist: httpx>=0.27.0
Requires-Dist: numpy>=1.24.0
Requires-Dist: posthog>=3.0.0
Requires-Dist: pydantic>=2.0.0
Requires-Dist: python-dotenv>=1.0.0
Requires-Dist: pyyaml>=6.0.0
Requires-Dist: requests>=2.31.0
Requires-Dist: rich>=13.0.0
Requires-Dist: scikit-learn>=1.3.0
Requires-Dist: sqlmodel>=0.0.14
Requires-Dist: trafilatura>=2.0.0
Provides-Extra: dev
Requires-Dist: pre-commit>=3.5.0; extra == 'dev'
Requires-Dist: pytest-asyncio>=0.24.0; extra == 'dev'
Requires-Dist: pytest-cov>=4.1.0; extra == 'dev'
Requires-Dist: pytest>=8.0.0; extra == 'dev'
Requires-Dist: ruff>=0.1.0; extra == 'dev'
Provides-Extra: eval
Requires-Dist: claude-agent-sdk>=0.1.6; extra == 'eval'
Requires-Dist: pytest-httpx>=0.30.0; extra == 'eval'
Requires-Dist: pyyaml>=6.0.0; extra == 'eval'
Requires-Dist: responses>=0.25.0; extra == 'eval'
